setup.py
digDrugUseExtractor/__init__.py
digDrugUseExtractor/drug_use_extractor.py
digDrugUseExtractor/extract_drug_use.py
digDrugUseExtractor.egg-info/PKG-INFO
digDrugUseExtractor.egg-info/SOURCES.txt
digDrugUseExtractor.egg-info/dependency_links.txt
digDrugUseExtractor.egg-info/requires.txt
digDrugUseExtractor.egg-info/top_level.txt
test/__init__.py
test/test_drug_use_extractor.py