Metadata-Version: 1.1
Name: digDrugUseExtractor
Version: 0.3.0
Summary: digDrugUseExtractor
Home-page: https://github.com/usc-isi-i2/dig-drug-use-extractor
Author: Lingzhe Teng
Author-email: zwein27@gmail.com
License: UNKNOWN
Download-URL: https://github.com/usc-isi-i2/dig-drug-use-extractor
Keywords: drug,use,extractor
Platform: UNKNOWN
